Workbook

Sheet Read me
A1: Month-end marketing pack
A2: SYNTHETIC Finance inputs: budgets and invoices are invented for demonstration. Delivered spend comes from the ad platform extracts.
A4: Month | B4: 2025-03
A5: As of (warehouse cursor) | B5: 2025-07-01
A6: Data through (last day of delivered spend) | B6: 2025-06-30
A7: Built by | B7: scripts/build_month_end_pack.py from data/marts/*.parquet
A9: Sheets
A10: Inputs | B10: Mart rows for the month, pasted as values. The only pasted numbers.
A11: Month_End | B11: All logic as formulas over Inputs, driven by the tolerance cell (B3).
A12: Checks | B12: TRUE/FALSE ties of the workbook against the marts. All must be TRUE.
A13: Commentary | B13: Plain-English summary, assembled by formulas.
A15: Definitions
A16: Delivered spend | B16: Ad platform spend for the month, days visible at the cursor. Blank where the channel has no cost source (TikTok).
A17: Media invoiced | B17: Platform media invoice lines for the month, received by the cursor.
A18: Fee invoiced | B18: Agency fee lines allocated to the channel (60/40 Meta/Google retainer). Not budgeted and not compared with delivered spend.
A19: Final invoice received | B19: A platform media invoice covering the whole month has arrived. It then replaces the estimate: accrual 0, recognised media = media invoiced (the true-up).
A20: Estimated unbilled accrual | B20: Before the final invoice: MAX(delivered - media invoiced, 0), delivered media not yet invoiced. After it: 0.
A21: Recognised media expense | B21: After the final invoice: media invoiced. Before it: MAX(delivered, media invoiced). Blank delivered: media invoiced if any.
A22: Recognised expense (incl. fees) | B22: Recognised media expense + fee invoiced.
A23: Approved media budget | B23: Latest budget version visible at the cursor. Budgets cover media only.
A24: Budget variance | B24: Recognised media expense - approved media budget. POSITIVE = OVERSPEND.
A25: Remaining budget | B25: Approved media budget - recognised media expense.
A26: Recon difference | B26: Media invoiced - delivered spend (positive: billed more than delivered).
A27: Recon status | B27: unallocated_cost, no_cost_source, unbilled (no media invoice yet), within_tolerance (|difference| <= tolerance), exception.
... A30: Limitations | B30: Synthetic Finance inputs. Channel grain only. No GL, journal entries or true-ups. Fees are recognised on receipt, never accrued.

Sheet Inputs
A1: channel | B1: approved_budget | C1: budget_version_used | D1: delivered_spend | E1: media_invoiced | F1: fee_invoiced | G1: estimated_unbilled_accrual | H1: recognised_media_expense | I1: recognised_expense | J1: budget_variance | K1: recon_difference | L1: recon_status | M1: data_status | N1: is_media_final
A2: meta | B2: 11250 | C2: original | D2: 10804.33 | E2: 11547.01 | F2: 1700 | G2: 0 | H2: 11547.01 | I2: 13247.01 | J2: 297.01 | K2: 742.68 | L2: exception | M2: source_gap | N2: =TRUE() -> TRUE
A3: google | B3: 8500 | C3: original | D3: 8608.79 | E3: 8637.19 | F3: 1133.33 | G3: 0 | H3: 8637.19 | I3: 9770.52 | J3: 137.19 | K3: 28.4 | L3: within_tolerance | M3: complete | N3: =TRUE() -> TRUE
A4: tiktok | B4: 1500 | C4: original | E4: 0 | F4: 0 | L4: no_cost_source | M4: no_cost_source | N4: =FALSE() -> FALSE
A6: Pasted as values from the dbt marts for 2025-03 (as of 2025-07-01). Blank = no data (NULL in the mart), never zero.
A7: SYNTHETIC Finance inputs: budgets and invoices are invented for demonstration. Delivered spend comes from the ad platform extracts.

Sheet Month_End
A1: Month-end marketing pack: 2025-03
A2: SYNTHETIC Finance inputs: budgets and invoices are invented for demonstration. Delivered spend comes from the ad platform extracts.
A3: Recon tolerance (%) | B3: 1 | C3: Input. Matches the dbt var recon_tolerance_pct. Change it to re-run the recon.
A4: Month | B4: ='Read me'!B4 -> 2025-03
A5: As of (cursor) | B5: ='Read me'!B5 -> 2025-07-01
A7: Channel | B7: Approved media budget | C7: Delivered spend | D7: Media invoiced | E7: Fee invoiced | F7: Estimated unbilled accrual | G7: Recognised media expense | H7: Recognised expense (incl. fees) | I7: Budget variance (+ = overspend) | J7: Budget variance % | K7: Remaining budget | L7: Recon difference (invoiced - delivered) | M7: Recon difference % | N7: Recon status | O7: Data status | P7: |Variance| (helper) | Q7: Budget with known spend (helper) | R7: Final invoice received (TRUE = true-up applied)
A8: =Inputs!A2 -> meta | B8: =IF(Inputs!B2="","",Inputs!B2) -> 11250 | C8: =IF(Inputs!D2="","",Inputs!D2) -> 10804.33 | D8: =SUMIFS(Inputs!$E$2:$E$4,Inputs!$A$2:$A$4,$A8) -> 11547.01 | E8: =SUMIFS(Inputs!$F$2:$F$4,Inputs!$A$2:$A$4,$A8) -> 1700 | F8: =IF(C8="","",IF(R8=TRUE(),0,ROUND(MAX(C8-D8,0),2))) -> 0 | G8: =IF(R8=TRUE(),D8,IF(C8="",IF(D8>0,D8,""),ROUND(MAX(C8,D8),2))) -> 11547.01 | H8: =IF(G8<>"",ROUND(G8+E8,2),IF(D8+E8>0,ROUND(D8+E8,2),"")) -> 13247.01 | I8: =IF(OR(B8="",G8=""),"",ROUND(G8-B8,2)) -> 297.01 | J8: =IF(I8="","",IF(B8=0,"",I8/B8)) -> 0.026400889 | K8: =IF(I8="","",ROUND(B8-G8,2)) -> -297.01 | L8: =IF(OR(C8="",D8=0),"",ROUND(D8-C8,2)) -> 742.68 | M8: =IF(L8="","",IF(C8=0,"",L8/C8)) -> 0.068739107 | N8: =IF($A8="unallocated","unallocated_cost",IF(C8="","no_cost_source",IF(D8=0,"unbilled",IF(ABS(D8-C8)<=ABS(C8)*$B$3/100,"within_tolerance","exception")))) -> exception | O8: =Inputs!M2 -> source_gap | P8: =IF(I8="","",ABS(I8)) -> 297.01 | Q8: =IF(I8="","",B8) -> 11250 | R8: =Inputs!N2 -> TRUE
A9: =Inputs!A3 -> google | B9: =IF(Inputs!B3="","",Inputs!B3) -> 8500 | C9: =IF(Inputs!D3="","",Inputs!D3) -> 8608.79 | D9: =SUMIFS(Inputs!$E$2:$E$4,Inputs!$A$2:$A$4,$A9) -> 8637.19 | E9: =SUMIFS(Inputs!$F$2:$F$4,Inputs!$A$2:$A$4,$A9) -> 1133.33 | F9: =IF(C9="","",IF(R9=TRUE(),0,ROUND(MAX(C9-D9,0),2))) -> 0 | G9: =IF(R9=TRUE(),D9,IF(C9="",IF(D9>0,D9,""),ROUND(MAX(C9,D9),2))) -> 8637.19 | H9: =IF(G9<>"",ROUND(G9+E9,2),IF(D9+E9>0,ROUND(D9+E9,2),"")) -> 9770.52 | I9: =IF(OR(B9="",G9=""),"",ROUND(G9-B9,2)) -> 137.19 | J9: =IF(I9="","",IF(B9=0,"",I9/B9)) -> 0.01614 | K9: =IF(I9="","",ROUND(B9-G9,2)) -> -137.19 | L9: =IF(OR(C9="",D9=0),"",ROUND(D9-C9,2)) -> 28.4 | M9: =IF(L9="","",IF(C9=0,"",L9/C9)) -> 0.0032989537 | N9: =IF($A9="unallocated","unallocated_cost",IF(C9="","no_cost_source",IF(D9=0,"unbilled",IF(ABS(D9-C9)<=ABS(C9)*$B$3/100,"within_tolerance","exception")))) -> within_tolerance | O9: =Inputs!M3 -> complete | P9: =IF(I9="","",ABS(I9)) -> 137.19 | Q9: =IF(I9="","",B9) -> 8500 | R9: =Inputs!N3 -> TRUE
A10: =Inputs!A4 -> tiktok | B10: =IF(Inputs!B4="","",Inputs!B4) -> 1500 | C10: =IF(Inputs!D4="","",Inputs!D4) | D10: =SUMIFS(Inputs!$E$2:$E$4,Inputs!$A$2:$A$4,$A10) -> 0 | E10: =SUMIFS(Inputs!$F$2:$F$4,Inputs!$A$2:$A$4,$A10) -> 0 | F10: =IF(C10="","",IF(R10=TRUE(),0,ROUND(MAX(C10-D10,0),2))) | G10: =IF(R10=TRUE(),D10,IF(C10="",IF(D10>0,D10,""),ROUND(MAX(C10,D10),2))) | H10: =IF(G10<>"",ROUND(G10+E10,2),IF(D10+E10>0,ROUND(D10+E10,2),"")) | I10: =IF(OR(B10="",G10=""),"",ROUND(G10-B10,2)) | J10: =IF(I10="","",IF(B10=0,"",I10/B10)) | K10: =IF(I10="","",ROUND(B10-G10,2)) | L10: =IF(OR(C10="",D10=0),"",ROUND(D10-C10,2)) | M10: =IF(L10="","",IF(C10=0,"",L10/C10)) | N10: =IF($A10="unallocated","unallocated_cost",IF(C10="","no_cost_source",IF(D10=0,"unbilled",IF(ABS(D10-C10)<=ABS(C10)*$B$3/100,"within_tolerance","exception")))) -> no_cost_source | O10: =Inputs!M4 -> no_cost_source | P10: =IF(I10="","",ABS(I10)) | Q10: =IF(I10="","",B10) | R10: =Inputs!N4 -> FALSE
A11: Total | B11: =SUM(B8:B10) -> 21250 | C11: =SUM(C8:C10) -> 19413.12 | D11: =SUM(D8:D10) -> 20184.2 | E11: =SUM(E8:E10) -> 2833.33 | F11: =SUM(F8:F10) -> 0 | G11: =SUM(G8:G10) -> 20184.2 | H11: =SUM(H8:H10) -> 23017.53 | I11: =SUM(I8:I10) -> 434.2 | J11: =IF(Q11=0,"",I11/Q11) -> 0.02198481 | K11: =SUM(K8:K10) -> -434.2 | L11: =SUM(L8:L10) -> 771.08 | Q11: =SUM(Q8:Q10) -> 19750
A13: Blank = no data, never zero. TikTok has no cost source, so its spend and variance are blank. Total variance % = total variance / budget of channels with known spend (a ratio of sums).

Sheet Checks
A1: Check | B1: Result
A2: Approved budget: Month_End total equals the pasted mart total | B2: =ROUND(Month_End!B11-SUM(Inputs!B2:B4),2)=0 -> TRUE
A3: Delivered spend: Month_End total equals the pasted mart total | B3: =ROUND(Month_End!C11-SUM(Inputs!D2:D4),2)=0 -> TRUE
A4: Media invoiced: Month_End total equals the pasted mart total | B4: =ROUND(Month_End!D11-SUM(Inputs!E2:E4),2)=0 -> TRUE
A5: Fee invoiced: Month_End total equals the pasted mart total | B5: =ROUND(Month_End!E11-SUM(Inputs!F2:F4),2)=0 -> TRUE
A6: meta: formula accrual equals the mart accrual | B6: =IF(AND(Month_End!F8="",Inputs!G2=""),TRUE(),IF(OR(Month_End!F8="",Inputs!G2=""),FALSE(),ROUND(Month_End!F8-Inputs!G2,2)=0)) -> TRUE
A7: meta: formula recognised media expense equals the mart | B7: =IF(AND(Month_End!G8="",Inputs!H2=""),TRUE(),IF(OR(Month_End!G8="",Inputs!H2=""),FALSE(),ROUND(Month_End!G8-Inputs!H2,2)=0)) -> TRUE
A8: meta: formula recognised expense equals the mart | B8: =IF(AND(Month_End!H8="",Inputs!I2=""),TRUE(),IF(OR(Month_End!H8="",Inputs!I2=""),FALSE(),ROUND(Month_End!H8-Inputs!I2,2)=0)) -> TRUE
A9: meta: formula budget variance equals the mart | B9: =IF(AND(Month_End!I8="",Inputs!J2=""),TRUE(),IF(OR(Month_End!I8="",Inputs!J2=""),FALSE(),ROUND(Month_End!I8-Inputs!J2,2)=0)) -> TRUE
A10: meta: formula recon difference equals the mart | B10: =IF(AND(Month_End!L8="",Inputs!K2=""),TRUE(),IF(OR(Month_End!L8="",Inputs!K2=""),FALSE(),ROUND(Month_End!L8-Inputs!K2,2)=0)) -> TRUE
A11: meta: formula recon status equals the mart | B11: =Month_End!N8=Inputs!L2 -> TRUE
A12: google: formula accrual equals the mart accrual | B12: =IF(AND(Month_End!F9="",Inputs!G3=""),TRUE(),IF(OR(Month_End!F9="",Inputs!G3=""),FALSE(),ROUND(Month_End!F9-Inputs!G3,2)=0)) -> TRUE
A13: google: formula recognised media expense equals the mart | B13: =IF(AND(Month_End!G9="",Inputs!H3=""),TRUE(),IF(OR(Month_End!G9="",Inputs!H3=""),FALSE(),ROUND(Month_End!G9-Inputs!H3,2)=0)) -> TRUE
A14: google: formula recognised expense equals the mart | B14: =IF(AND(Month_End!H9="",Inputs!I3=""),TRUE(),IF(OR(Month_End!H9="",Inputs!I3=""),FALSE(),ROUND(Month_End!H9-Inputs!I3,2)=0)) -> TRUE
A15: google: formula budget variance equals the mart | B15: =IF(AND(Month_End!I9="",Inputs!J3=""),TRUE(),IF(OR(Month_End!I9="",Inputs!J3=""),FALSE(),ROUND(Month_End!I9-Inputs!J3,2)=0)) -> TRUE
A16: google: formula recon difference equals the mart | B16: =IF(AND(Month_End!L9="",Inputs!K3=""),TRUE(),IF(OR(Month_End!L9="",Inputs!K3=""),FALSE(),ROUND(Month_End!L9-Inputs!K3,2)=0)) -> TRUE
A17: google: formula recon status equals the mart | B17: =Month_End!N9=Inputs!L3 -> TRUE
A18: tiktok: formula accrual equals the mart accrual | B18: =IF(AND(Month_End!F10="",Inputs!G4=""),TRUE(),IF(OR(Month_End!F10="",Inputs!G4=""),FALSE(),ROUND(Month_End!F10-Inputs!G4,2)=0)) -> TRUE
A19: tiktok: formula recognised media expense equals the mart | B19: =IF(AND(Month_End!G10="",Inputs!H4=""),TRUE(),IF(OR(Month_End!G10="",Inputs!H4=""),FALSE(),ROUND(Month_End!G10-Inputs!H4,2)=0)) -> TRUE
A20: tiktok: formula recognised expense equals the mart | B20: =IF(AND(Month_End!H10="",Inputs!I4=""),TRUE(),IF(OR(Month_End!H10="",Inputs!I4=""),FALSE(),ROUND(Month_End!H10-Inputs!I4,2)=0)) -> TRUE
A21: tiktok: formula budget variance equals the mart | B21: =IF(AND(Month_End!I10="",Inputs!J4=""),TRUE(),IF(OR(Month_End!I10="",Inputs!J4=""),FALSE(),ROUND(Month_End!I10-Inputs!J4,2)=0)) -> TRUE
A22: tiktok: formula recon difference equals the mart | B22: =IF(AND(Month_End!L10="",Inputs!K4=""),TRUE(),IF(OR(Month_End!L10="",Inputs!K4=""),FALSE(),ROUND(Month_End!L10-Inputs!K4,2)=0)) -> TRUE
A23: tiktok: formula recon status equals the mart | B23: =Month_End!N10=Inputs!L4 -> TRUE
A25: ALL CHECKS PASS | B25: =AND(B2:B23) -> TRUE
A26: Recalculates on open. The recon status checks assume the tolerance is left at the dbt default.

Sheet Commentary
A1: Commentary: 2025-03
A3: ="These figures use SYNTHETIC Finance inputs (invented budgets and invoices) and are for demonstration only." -> These figures use SYNTHETIC Finance inputs (invented budgets and invoices) and are for demonstration only.
A4: =IF(COUNT(Month_End!$P$8:$P$10)=0,"No channel has both a media budget and known spend this month.","The largest budget variance in "&Month_End!$B$4&" is "&SUBSTITUTE(PROPER(INDEX(Month_End!$A$8:$A$10,MATCH(MAX(Month_End!$P$8:$P$10),Month_End!$P$8:$P$10,0))),"Tiktok","TikTok")&" at £"&TEXT(ABS(INDEX(Month_End!$I$8:$I$10,MATCH(MAX(Month_End!$P$8:$P$10),Month_End!$P$8:$P$10,0))),"#,##0")&" ("&TEXT(ABS(INDEX(Month_End!$J$8:$J$10,MATCH(MAX(Month_End!$P$8:$P$10),Month_End!$P$8:$P$10,0))),"0.0%")&"), "&IF(INDEX(Month_End!$I$8:$I$10,MATCH(MAX(Month_End!$P$8:$P$10),Month_End!$P$8:$P$10,0))>0,"an overspend","an underspend")&" against its media budget.") -> The largest budget variance in 2025-03 is Meta at £297 (2.6%), an overspend against its media budget.
A5: =IF(COUNTIF(Month_End!$N$8:$N$10,"no_cost_source")=0,"",SUBSTITUTE(PROPER(INDEX(Month_End!$A$8:$A$10,MATCH("no_cost_source",Month_End!$N$8:$N$10,0))),"Tiktok","TikTok")&" has an approved budget of £"&TEXT(INDEX(Month_End!$B$8:$B$10,MATCH("no_cost_source",Month_End!$N$8:$N$10,0)),"#,##0")&" but no cost source, so its spend and variance are unknown (left blank), not zero.") -> TikTok has an approved budget of £1,500 but no cost source, so its spend and variance are unknown (left blank), not zero.
A6: =IF(COUNTIF(Month_End!$N$8:$N$10,"exception")>0,"Main risk: the "&SUBSTITUTE(PROPER(INDEX(Month_End!$A$8:$A$10,MATCH("exception",Month_End!$N$8:$N$10,0))),"Tiktok","TikTok")&" invoice differs from delivered spend by "&TEXT(ABS(INDEX(Month_End!$M$8:$M$10,MATCH("exception",Month_End!$N$8:$N$10,0))),"0.0%")&", above the "&TEXT(Month_End!$B$3,"0.0")&"% tolerance."&IF(INDEX(Month_End!$O$8:$O$10,MATCH("exception",Month_End!$N$8:$N$10,0))="source_gap"," The spend extract is missing days for this month, which may explain the gap.",""),IF(COUNTIF(Month_End!$N$8:$N$10,"unbilled")>0,"Main risk: £"&TEXT(SUM(Month_End!$F$8:$F$10),"#,##0")&" of delivered media is not yet invoiced and is carried as an estimated accrual until the invoices arrive.","Main risk: none flagged. Every platform invoice is within the "&TEXT(Month_End!$B$3,"0.0")&"% tolerance.")) -> Main risk: the Meta invoice differs from delivered spend by 6.9%, above the 1.0% tolerance. The spend extract is missing days for this month, which may explain the gap.
A7: =IF(COUNTIF(Month_End!$N$8:$N$10,"exception")>0,IF(INDEX(Month_End!$O$8:$O$10,MATCH("exception",Month_End!$N$8:$N$10,0))="source_gap","Recommended action: obtain the missing days of spend from the platform and re-run the reconciliation before querying the invoice.","Recommended action: query the "&SUBSTITUTE(PROPER(INDEX(Month_End!$A$8:$A$10,MATCH("exception",Month_End!$N$8:$N$10,0))),"Tiktok","TikTok")&" invoice with the platform before approving it for payment."),IF(COUNTIF(Month_End!$N$8:$N$10,"unbilled")>0,"Recommended action: post the £"&TEXT(SUM(Month_End!$F$8:$F$10),"#,##0")&" accrual and replace it with the actual invoices when they arrive early next month.","Recommended action: none beyond normal review."))&IF(COUNTIF(Month_End!$N$8:$N$10,"unallocated_cost")>0," Also allocate the £"&TEXT(SUMIFS(Month_End!$H$8:$H$10,Month_End!$N$8:$N$10,"unallocated_cost"),"#,##0")&" of invoiced cost that has no channel.","") -> Recommended action: obtain the missing days of spend from the platform and re-run the reconciliation before querying the invoice.
A9: Each sentence is a formula over Month_End, so it updates if Inputs or the tolerance change.
